cht_cyclones/__init__.py
cht_cyclones/cyclone_track_database.py
cht_cyclones/ensemble.py
cht_cyclones/fileio.py
cht_cyclones/fit_holland_2010.py
cht_cyclones/spiderweb.py
cht_cyclones/track.py
cht_cyclones/track_database.py
cht_cyclones/track_dataset.py
cht_cyclones/track_selector.py
cht_cyclones/tropical_cyclone.py
cht_cyclones/tropical_cyclone_refactored.py
cht_cyclones/utils.py
cht_cyclones/wind_profiles.py
cht_cyclones-1.0.3.dist-info/LICENSE
cht_cyclones-1.0.3.dist-info/METADATA
cht_cyclones-1.0.3.dist-info/WHEEL
cht_cyclones-1.0.3.dist-info/top_level.txt
cht_cyclones-1.0.3.dist-info/zip-safe
cht_cyclones-1.0.3.dist-info/RECORD
